cv_reality_check-0.2.35.dist-info/licenses/LICENSE
cvguard/__init__.py
cvguard/adv_validation.py
cvguard/api.py
cvguard/config.py
cvguard/cv_schemes.py
cvguard/data_utils.py
cvguard/drift_analysis.py
cvguard/leakage_checks.py
cvguard/metrics.py
cvguard/oof_estimation.py
cvguard/recommendations.py
cvguard/report_generator.py
cvguard/scoring.py
cv_reality_check-0.2.35.dist-info/METADATA
cv_reality_check-0.2.35.dist-info/WHEEL
cv_reality_check-0.2.35.dist-info/top_level.txt
cv_reality_check-0.2.35.dist-info/RECORD
