Metadata-Version: 2.4
Name: CV-reality-check
Version: 0.2.35
Summary: Kaggle-oriented cross-validation reliability checker
Project-URL: Homepage, https://github.com/artwmana/CV-reality-check
Project-URL: Issues, https://github.com/artwmana/CV-reality-check/issues
Requires-Python: >=3.9
License-File: LICENSE
Requires-Dist: numpy>=1.24
Requires-Dist: pandas>=1.5
Requires-Dist: scikit-learn>=1.3
Requires-Dist: scipy>=1.10
Requires-Dist: lightgbm>=4.0; extra == "full"
Provides-Extra: full
Requires-Dist: lightgbm>=4.0; extra == "full"
Dynamic: license-file
